<Manifest><order_reference>OPTIONAL NEW Order Reference</order_reference><shipments><customer_reference_1>refence text 1</customer_reference_1><customer_reference_2>refence text 2</customer_reference_2><items><item_reference>OPTIONAL NEW Item Reference</item_reference><weight>20</weight><height>5</height><product_id>T28S</product_id><tracking_details></tracking_details><width>5</width><features><attributes><amount>3000.00</amount></attributes><type>TRANSIT_COVER</type></features><length>5</length><contains_dangerous_goods>true</contains_dangerous_goods></items><items><item_reference>OPTIONAL NEW Item Reference</item_reference><weight>20</weight><height>5</height><product_id>T28S</product_id><tracking_details></tracking_details><width>5</width><features><attributes><amount>3000.00</amount></attributes><type>TRANSIT_COVER</type></features><length>5</length><contains_dangerous_goods>false</contains_dangerous_goods></items><items><item_reference>OPTIONAL NEW Item Reference</item_reference><weight>20</weight><height>5</height><product_id>T28S</product_id><tracking_details></tracking_details><width>5</width><features><attributes><amount>3000.00</amount></attributes><type>TRANSIT_COVER</type></features><length>5</length><contains_dangerous_goods>true</contains_dangerous_goods></items><lodgement><business_name>Hello World Pty Ltd</business_name><suburb>Port Melbourne</suburb><name>ATTN: Steve</name><state>NSW</state><lines>Corporate HQ</lines><lines>123 Fake St</lines><postcode>2170</postcode></lodgement><shipment_reference>OPTIONAL NEW Shipment Reference</shipment_reference><destination><business_name>Hello World Pty Ltd</business_name><delivery_instructions>delivery instruction text</delivery_instructions><suburb>Melbourne</suburb><name>ATTN: Paul</name><state>NSW</state><lines>111 Bourke Street</lines><postcode>2170</postcode></destination></shipments><contract_id>0007032406</contract_id><payment_method>CREDIT_CARD</payment_method></Manifest>